<?xml version="1.0" ?>
<cardsflow>
	<myoMuscle name="motor0">
		<link name="bike">
			<viaPoint type="FIXPOINT">1.1244910048466528 -0.1865722443407175 0.7209656429956216</viaPoint>
		</link>
		<link name="thigh_left">
			<viaPoint type="FIXPOINT">-0.03262587979868542 0.024405678040797022 0.026560495796001577</viaPoint>
		</link>
	</myoMuscle>
	<myoMuscle name="motor1">
		<link name="bike">
			<viaPoint type="FIXPOINT">1.2149351840927745 -0.18557224434751418 0.7217326988413734</viaPoint>
		</link>
		<link name="thigh_left">
			<viaPoint type="FIXPOINT">0.07174274356776443 0.027405677995026016 0.12155868730253083</viaPoint>
			<viaPoint type="FIXPOINT">0.02736266955384032 0.024405678040086906 0.027732650469902326</viaPoint>
		</link>
	</myoMuscle>
	<myoMuscle name="motor2">
		<link name="bike">
			<viaPoint type="FIXPOINT">1.140500707699969 -0.18705725503425008 0.4766761427688282</viaPoint>
		</link>
		<link name="leg_left">
			<viaPoint type="FIXPOINT">-0.08310092771141629 0.026669360645421653 0.15069862454787564</viaPoint>
			<viaPoint type="FIXPOINT">-0.028649064915268453 0.023669360712901568 0.02944854358227971</viaPoint>
		</link>
	</myoMuscle>
	<myoMuscle name="motor3">
		<link name="bike">
			<viaPoint type="FIXPOINT">1.2099166425611472 -0.18532834862848732 0.47757640483027175</viaPoint>
		</link>
		<link name="thigh_left">
			<viaPoint type="FIXPOINT">0.03410255894332053 0.024605678121444027 -0.3172015083418009</viaPoint>
		</link>
	</myoMuscle>
	<myoMuscle name="motor4">
		<link name="leg_left">
			<viaPoint type="FIXPOINT">-0.03196321966420488 0.025182566944706365 -0.06800096348548973</viaPoint>
		</link>
		<link name="foot_left">
			<viaPoint type="FIXPOINT">-0.015284701941058146 8.061817879934097e-13 0.010600843672699431</viaPoint>
		</link>
	</myoMuscle>
	<myoMuscle name="motor5">
		<link name="leg_left">
			<viaPoint type="FIXPOINT">0.03908755527389296 0.022166719147746646 -0.069797099032515</viaPoint>
		</link>
		<link name="foot_left">
			<viaPoint type="FIXPOINT">0.11193473872682709 -1.8209114216460875e-11 0.003951489106254933</viaPoint>
		</link>
	</myoMuscle>
	<myoMuscle name="motor6">
		<link name="bike">
			<viaPoint type="FIXPOINT">1.1244458545998446 0.1578099662312663 0.7209647609395553</viaPoint>
		</link>
		<link name="thigh_right">
			<viaPoint type="FIXPOINT">-0.032654818346348584 -0.02440782180500552 0.02656029161869597</viaPoint>
		</link>
	</myoMuscle>
	<myoMuscle name="motor7">
		<link name="bike">
			<viaPoint type="FIXPOINT">1.2130050170843256 0.15820627869831122 0.7227051920259667</viaPoint>
		</link>
		<link name="thigh_right">
			<viaPoint type="FIXPOINT">0.07171380511072321 -0.0274078218496091 0.12155848302276852</viaPoint>
			<viaPoint type="FIXPOINT">0.02733373100729587 -0.02440782180527922 0.027732446235345664</viaPoint>
		</link>
	</myoMuscle>
	<myoMuscle name="motor8">
		<link name="thigh_right">
			<viaPoint type="FIXPOINT">0.035076743629558677 -0.02285492486564966 -0.07242648210822943</viaPoint>
		</link>
		<link name="leg_right">
			<viaPoint type="FIXPOINT">0.031060594712265657 -0.023637442901514233 0.030932016681161727</viaPoint>
		</link>
	</myoMuscle>
	<myoMuscle name="motor9">
		<link name="thigh_right">
			<viaPoint type="FIXPOINT">-0.03522158720383192 -0.02561662797499082 -0.0713262209756001</viaPoint>
		</link>
		<link name="leg_right">
			<viaPoint type="FIXPOINT">-0.08446979081249843 -0.02663744296393549 0.1499616194485494</viaPoint>
			<viaPoint type="FIXPOINT">-0.02891477524066435 -0.0236374429009566 0.029213005625596367</viaPoint>
		</link>
	</myoMuscle>
	<myoMuscle name="motor10">
		<link name="leg_right">
			<viaPoint type="FIXPOINT">-0.03181646355660327 -0.02213480122614584 -0.07146145398858401</viaPoint>
		</link>
		<link name="foot_right">
			<viaPoint type="FIXPOINT">-0.015003317027338347 -4.9664450330055845e-12 0.01099547535021489</viaPoint>
		</link>
	</myoMuscle>
	<myoMuscle name="motor11">
		<link name="leg_right">
			<viaPoint type="FIXPOINT">0.03963144017497562 -0.02522185265491025 -0.0661873495932068</viaPoint>
		</link>
		<link name="foot_right">
			<viaPoint type="FIXPOINT">0.11199969329579648 -1.0237712899652251e-11 0.0010337802704686828</viaPoint>
		</link>
	</myoMuscle>
	<myoMuscle name="motor12">
		<link name="torso">
			<viaPoint type="FIXPOINT">0.0008245253033303257 -0.28653890798784193 0.07450627641315351</viaPoint>
		</link>
		<link name="upper_arm_left">
			<viaPoint type="FIXPOINT">-0.025483658242399444 0.072262184285132 0.07348135643868915</viaPoint>
		</link>
	</myoMuscle>
	<myoMuscle name="motor13">
		<link name="torso">
			<viaPoint type="FIXPOINT">-0.011863826472648747 -0.2376332102176052 -0.03472303374910581</viaPoint>
		</link>
		<link name="upper_arm_left">
			<viaPoint type="FIXPOINT">-0.022914125153439074 0.09775652819549517 0.045504613140622326</viaPoint>
		</link>
	</myoMuscle>
	<myoMuscle name="motor14">
		<link name="torso">
			<viaPoint type="FIXPOINT">-0.01594455561304585 -0.2488158290334617 0.012471302487519723</viaPoint>
		</link>
		<link name="upper_arm_left">
			<viaPoint type="FIXPOINT">-0.034375937156987356 0.08569514775831898 0.057351517135296605</viaPoint>
		</link>
	</myoMuscle>
	<myoMuscle name="motor15">
		<link name="torso">
			<viaPoint type="FIXPOINT">-0.01666024156219219 -0.27823446866715457 0.055906936562567185</viaPoint>
		</link>
		<link name="upper_arm_left">
			<viaPoint type="FIXPOINT">-0.0009535449947985342 0.06692762282180055 0.0810757274993415</viaPoint>
		</link>
	</myoMuscle>
	<myoMuscle name="motor16">
		<link name="torso">
			<viaPoint type="FIXPOINT">0.05479080784172186 -0.2745849497429432 0.05570658515457239</viaPoint>
		</link>
		<link name="upper_arm_left">
			<viaPoint type="FIXPOINT">-0.0059426794571873385 0.06667279184607906 0.08108971721849258</viaPoint>
		</link>
	</myoMuscle>
	<myoMuscle name="motor17">
		<link name="torso">
			<viaPoint type="FIXPOINT">0.055646834640521836 -0.24515914189281598 0.012270557558540247</viaPoint>
		</link>
		<link name="upper_arm_left">
			<viaPoint type="FIXPOINT">0.01816868217486082 0.07510777259110996 0.07264242663634093</viaPoint>
		</link>
	</myoMuscle>
	<myoMuscle name="motor18">
		<link name="torso">
			<viaPoint type="FIXPOINT">0.06372234054537383 -0.2337724810996677 -0.03493498018114991</viaPoint>
		</link>
		<link name="upper_arm_left">
			<viaPoint type="FIXPOINT">0.012600097127844023 0.0988108038456533 0.04475369809977337</viaPoint>
		</link>
	</myoMuscle>
	<myoMuscle name="motor19">
		<link name="torso">
			<viaPoint type="FIXPOINT">0.03758495355859704 -0.28413798579574073 0.07511071734067457</viaPoint>
		</link>
		<link name="upper_arm_left">
			<viaPoint type="FIXPOINT">0.01905576148440062 0.07481334422643862 0.07303515251901985</viaPoint>
		</link>
	</myoMuscle>
	<myoMuscle name="motor20">
		<link name="upper_arm_left">
			<viaPoint type="FIXPOINT">-0.035658683735727725 -0.0515486171809188 -0.05940787332984428</viaPoint>
		</link>
		<link name="lower_arm_left">
			<viaPoint type="FIXPOINT">-0.04080356510811669 0.1019352794631454 0.09025189783579435</viaPoint>
		</link>
	</myoMuscle>
	<myoMuscle name="motor21">
		<link name="upper_arm_left">
			<viaPoint type="FIXPOINT">0.03874148349818341 -0.06384151020582919 -0.07229472301247312</viaPoint>
		</link>
		<link name="lower_arm_left">
			<viaPoint type="FIXPOINT">0.026555737147070317 0.12133949455971291 0.1041149839481588</viaPoint>
		</link>
	</myoMuscle>
	<myoMuscle name="motor22">
		<link name="torso">
			<viaPoint type="FIXPOINT">0.0007943283879064822 0.2913448188613429 0.07450636136075162</viaPoint>
		</link>
		<link name="upper_arm_left">
			<viaPoint type="FIXPOINT">-0.02583903607335923 0.7582333141010744 0.07211449440897554</viaPoint>
		</link>
	</myoMuscle>
	<myoMuscle name="motor23">
		<link name="torso">
			<viaPoint type="FIXPOINT">-0.011863826464444713 0.24243757882066777 -0.03472303352123902</viaPoint>
		</link>
	</myoMuscle>
	<myoMuscle name="motor24">
		<link name="upper_arm_left">
			<viaPoint type="FIXPOINT">-0.022578241527571735 0.7347166105104067 0.04494238069394186</viaPoint>
		</link>
	</myoMuscle>
	<myoMuscle name="motor25">
		<link name="torso">
			<viaPoint type="FIXPOINT">-0.015944555604947154 0.25362019759167853 0.012471302726003443</viaPoint>
		</link>
		<link name="upper_arm_left">
			<viaPoint type="FIXPOINT">-0.034496016623765585 0.7456185736087569 0.0584848777766868</viaPoint>
		</link>
	</myoMuscle>
	<myoMuscle name="motor26">
		<link name="torso">
			<viaPoint type="FIXPOINT">-0.01669043847753784 0.2830403795581495 0.05590702150228083</viaPoint>
		</link>
		<link name="upper_arm_left">
			<viaPoint type="FIXPOINT">-0.023036558551608445 0.7607340893842226 0.07518227639944002</viaPoint>
		</link>
	</myoMuscle>
	<myoMuscle name="motor28">
		<link name="torso">
			<viaPoint type="FIXPOINT">0.054760610926410574 0.2793908606348014 0.055706670090820865</viaPoint>
		</link>
		<link name="upper_arm_left">
			<viaPoint type="FIXPOINT">0.015659475180967705 0.7587576046643532 0.07507377127543009</viaPoint>
		</link>
	</myoMuscle>
	<myoMuscle name="motor29">
		<link name="torso">
			<viaPoint type="FIXPOINT">0.055646834648655 0.2499635104518978 0.012270557793551974</viaPoint>
		</link>
		<link name="upper_arm_left">
			<viaPoint type="FIXPOINT">0.02544678791659763 0.7449458559484525 0.05956081215448734</viaPoint>
		</link>
	</myoMuscle>
	<myoMuscle name="motor30">
		<link name="torso">
			<viaPoint type="FIXPOINT">0.06372234055361428 0.2385768497036436 -0.034934979956948664</viaPoint>
		</link>
		<link name="upper_arm_left">
			<viaPoint type="FIXPOINT">0.012606781350581926 0.7322821508152996 0.04410234782126935</viaPoint>
		</link>
	</myoMuscle>
	<myoMuscle name="motor32">
		<link name="upper_arm_right">
			<viaPoint type="FIXPOINT">-0.036168011360957805 0.04614540936555713 -0.053130660083950544</viaPoint>
		</link>
		<link name="lower_arm_right">
			<viaPoint type="FIXPOINT">-0.040103241359352886 -0.10434944281990831 0.0922768763990993</viaPoint>
		</link>
	</myoMuscle>
	<myoMuscle name="motor31">
		<link name="upper_arm_right">
			<viaPoint type="FIXPOINT">0.04404952061410412 0.044610363043985045 -0.04969596615654012</viaPoint>
		</link>
		<link name="lower_arm_right">
			<viaPoint type="FIXPOINT">0.02641796230286239 -0.12415461364759586 0.10627583068629334</viaPoint>
		</link>
	</myoMuscle>
	<myoMuscle name="motor27">
		<link name="torso">
			<viaPoint type="FIXPOINT">0.011200555915699547 0.3125009896715997 0.0906593428660031</viaPoint>
		</link>
		<link name="upper_arm_right">
			<viaPoint type="FIXPOINT">-0.0035186410303940365 -0.06553161114576789 0.08096960225515261</viaPoint>
		</link>
	</myoMuscle>
</cardsflow>
